abstract/__init__.py
abstract/literal.py
abstract/namespace.py
abstract/resource.py
abstract/uri.py
dua/__init__.py
dua/constants.py
dua/generator.py
dua/resource.py
synthea_rdf/__init__.py
synthea_rdf/graph.py
synthea_rdf/memory.py
synthea_rdf/resource.py
synthea_rdf/settings.py
trustscore/__init__.py
trustscore/generator.py
trustscore/resource.py
synthea_rdf-0.2.dist-info/LICENSE
synthea_rdf-0.2.dist-info/METADATA
synthea_rdf-0.2.dist-info/WHEEL
synthea_rdf-0.2.dist-info/top_level.txt
synthea_rdf-0.2.dist-info/RECORD
