Metadata-Version: 2.1
Name: synthea-rdf
Version: 0.2
Summary: Semantic web representation for the Synthea.
Author: Dae-young Kim, James Clavin
Author-email: leroy.kim@umbc.edu, jclavin@umbc.edu
License: GPLv3
Project-URL: Source Code, https://github.com/leroykim/synthea-rdf
Classifier: Programming Language :: Python :: 3
Classifier: License :: OSI Approved :: GNU General Public License v3 (GPLv3)
Classifier: Operating System :: OS Independent
License-File: LICENSE
Requires-Dist: rdflib
Requires-Dist: pandas
Requires-Dist: alive-progress
Requires-Dist: panel
Requires-Dist: lorem-text
Requires-Dist: pyyaml
